Metadata-Version: 2.1
Name: dimetadata-api
Version: 0.0.2
Summary: Python package using SAP Metadata Management API Business HUB.
Home-page: https://github.com/thhapke/dimetadata_api/
Author: Thorsten Hapke
Author-email: thorsten.hapke@sap.com
License: UNKNOWN
Project-URL: SAP Metadata Management API, https://api.sap.com/api/metadata/overview
Platform: UNKNOWN
Classifier: Programming Language :: Python :: 3.9
Classifier: License :: OSI Approved :: Apache Software License
Classifier: Operating System :: OS Independent
Requires-Python: >=3.6
License-File: LICENSE
